{
  "id": "1fd72dfc-323f-4651-b5ff-b4fb19d7a35f",
  "content": "A not-for-profit organization, IEEE is the world's largest technical professional organization dedicated to advancing technology for the benefit of humanity.  Copyright 2026 IEEE - All rights reserved. Use of this web site signifies your agreement to the terms and conditions.",
  "metadata": {
    "keywords": [
      "organization",
      "ieee",
      "2026",
      "notforprofit",
      "worlds",
      "largest",
      "technical",
      "professional",
      "dedicated",
      "advancing",
      "technology",
      "benefit",
      "humanity",
      "copyright",
      "rights",
      "reserved",
      "site",
      "signifies",
      "your",
      "agreement"
    ],
    "language": "en-US",
    "wordCount": 40,
    "readingTime": 1,
    "summary": "A not-for-profit organization, IEEE is the world's largest technical professional organization dedicated to advancing technology for the benefit of humanity",
    "readability": {
      "wordCount": 40,
      "sentenceCount": 3,
      "avgWordsPerSentence": 13.333333333333334,
      "readingTime": 1
    },
    "quality": {
      "score": 60,
      "reasons": [
        "Has title",
        "Rich metadata",
        "Contains useful links",
        "Contains boilerplate content",
        "Medium quality content"
      ]
    },
    "originalUrl": "https://ieeexplore.ieee.org/browse/books/title/Mechatronics",
    "processedAt": "2026-03-03T09:25:10.079Z"
  },
  "source": "https://ieeexplore.ieee.org/browse/books/title/Mechatronics",
  "timestamp": "2026-03-03T09:25:10.079Z",
  "category": "technology",
  "tags": [
    "organization",
    "ieee",
    "2026",
    "notforprofit",
    "worlds"
  ]
}