{
  "id": "37cf8d43-f7e5-40c2-bc69-870a403be90e",
  "content": "Beverage and cannabis company Tilray acquires the brewery, the brand and 11 bars after Brewdog went into administration.",
  "metadata": {
    "pubDate": "Mon, 02 Mar 2026 18:47:45 GMT",
    "author": "",
    "guid": "https://www.bbc.com/news/articles/c05v0p1d0peo#2",
    "feedTitle": "BBC News",
    "summary": "Beverage and cannabis company Tilray acquires the brewery, the brand and 11 bars after Brewdog went into administration",
    "keywords": [
      "beverage",
      "cannabis",
      "company",
      "tilray",
      "acquires",
      "brewery",
      "brand",
      "bars",
      "after",
      "brewdog",
      "went",
      "into",
      "administration"
    ],
    "readability": {
      "wordCount": 18,
      "sentenceCount": 1,
      "avgWordsPerSentence": 18,
      "readingTime": 1
    },
    "quality": {
      "score": 65,
      "reasons": [
        "Has title",
        "Rich metadata",
        "Medium quality content"
      ]
    },
    "originalUrl": "https://www.bbc.com/news/articles/c05v0p1d0peo?at_medium=RSS&at_campaign=rss",
    "processedAt": "2026-03-03T09:40:43.291Z"
  },
  "source": "https://www.bbc.com/news/articles/c05v0p1d0peo?at_medium=RSS&at_campaign=rss",
  "timestamp": "2026-03-03T09:40:43.300Z",
  "category": "news",
  "tags": [
    "beverage",
    "cannabis",
    "company",
    "tilray",
    "acquires"
  ]
}