{
  "id": "9114197b-fab3-4a2d-b1e2-7cfc76ceddb4",
  "content": "Ben Chu has been looking at what s happened to marine traffic in the Strait of Hormuz, a key trade passage.",
  "metadata": {
    "pubDate": "Mon, 02 Mar 2026 21:21:05 GMT",
    "author": "",
    "guid": "https://www.bbc.com/news/videos/cvgjnv2y90wo#1",
    "feedTitle": "BBC News",
    "summary": "Ben Chu has been looking at what s happened to marine traffic in the Strait of Hormuz, a key trade passage",
    "keywords": [
      "looking",
      "what",
      "happened",
      "marine",
      "traffic",
      "strait",
      "hormuz",
      "trade",
      "passage"
    ],
    "readability": {
      "wordCount": 21,
      "sentenceCount": 1,
      "avgWordsPerSentence": 21,
      "readingTime": 1
    },
    "quality": {
      "score": 65,
      "reasons": [
        "Has title",
        "Rich metadata",
        "Medium quality content"
      ]
    },
    "originalUrl": "https://www.bbc.com/news/videos/cvgjnv2y90wo?at_medium=RSS&at_campaign=rss",
    "processedAt": "2026-03-03T11:04:38.243Z"
  },
  "source": "https://www.bbc.com/news/videos/cvgjnv2y90wo?at_medium=RSS&at_campaign=rss",
  "timestamp": "2026-03-03T11:04:38.244Z",
  "category": "news",
  "tags": [
    "looking",
    "what",
    "happened",
    "marine",
    "traffic"
  ]
}