{
  "id": "f494c165-17b9-42f4-bdd3-a3c14d21b51b",
  "content": "Currently, Australia is the only continent in the world still free from the highly contagious H5 bird flu. But that status faces an ongoing threat.",
  "metadata": {
    "pubDate": "Mon, 02 Mar 2026 21:40:01 EST",
    "author": "",
    "guid": "news691669269",
    "feedTitle": "Phys.org - latest science and technology news stories",
    "categories": [
      "Veterinary medicine"
    ],
    "summary": "Currently, Australia is the only continent in the world still free from the highly contagious H5 bird flu. But that status faces an ongoing threat",
    "keywords": [
      "currently",
      "australia",
      "only",
      "continent",
      "world",
      "still",
      "free",
      "from",
      "highly",
      "contagious",
      "bird",
      "flu",
      "status",
      "faces",
      "ongoing",
      "threat"
    ],
    "readability": {
      "wordCount": 25,
      "sentenceCount": 2,
      "avgWordsPerSentence": 12.5,
      "readingTime": 1
    },
    "quality": {
      "score": 65,
      "reasons": [
        "Has title",
        "Rich metadata",
        "Medium quality content"
      ]
    },
    "originalUrl": "https://phys.org/news/2026-03-simulation-australia-h5-bird-flu.html",
    "processedAt": "2026-03-03T10:32:25.541Z"
  },
  "source": "https://phys.org/news/2026-03-simulation-australia-h5-bird-flu.html",
  "timestamp": "2026-03-03T10:32:25.578Z",
  "category": "news",
  "tags": [
    "currently",
    "australia",
    "only",
    "continent",
    "world"
  ]
}